rs_chardet-0.2.2.dist-info/METADATA
rs_chardet-0.2.2.dist-info/WHEEL
rs_chardet-0.2.2.dist-info/license_files/LICENSE.txt
rs_chardet/__init__.py
rs_chardet/rs_chardet.abi3.so
rs_chardet-0.2.2.dist-info/RECORD
