Metadata-Version: 2.1
Name: rs-chardet
Version: 0.2.2
Classifier: Development Status :: 3 - Alpha
Classifier: Intended Audience :: Developers
Classifier: License :: OSI Approved :: MIT License
Classifier: Topic :: Software Development
Classifier: Topic :: Software Development :: Libraries
Classifier: Topic :: Software Development :: Libraries :: Python Modules
Classifier: Programming Language :: Rust
Classifier: Programming Language :: Python :: Implementation :: CPython
Classifier: Programming Language :: Python :: Implementation :: PyPy
License-File: LICENSE.txt
Author: Evan Mattiza
License: MIT
Requires-Python: >=3.8
Project-URL: repository, https://github.com/emattiza/rs_chardet
Project-URL: homepage, https://github.com/emattiza/rs_chardet
Project-URL: documentation, https://github.com/emattiza/rs_chardet/README.md
